pycdfpp/__init__.py
pycdfpp/_pycdfpp.cpython-314-aarch64-linux-gnu.so
pycdfpp-0.8.6.dist-info/COPYING
pycdfpp-0.8.6.dist-info/METADATA
pycdfpp-0.8.6.dist-info/WHEEL
pycdfpp-0.8.6.dist-info/RECORD
