Metadata-Version: 2.1
Name: pycdfpp
Version: 0.8.6
Summary: A modern C++ header only cdf library
Author-Email: Alexis Jeandet <alexis.jeandet@member.fsf.org>
License: MIT License
Classifier: Development Status :: 5 - Production/Stable
Classifier: Intended Audience :: Developers
Classifier: License :: OSI Approved :: MIT License
Classifier: Natural Language :: English
Classifier: Programming Language :: Python :: 3
Classifier: Programming Language :: Python :: 3.9
Classifier: Programming Language :: Python :: 3.10
Classifier: Programming Language :: Python :: 3.11
Classifier: Programming Language :: Python :: 3.12
Classifier: Programming Language :: Python :: 3.13
Project-URL: homepage, https://github.com/SciQLop/CDFpp
Project-URL: documentation, https://pycdfpp.readthedocs.io/en/latest/
Project-URL: repository, https://github.com/SciQLop/CDFpp
Requires-Python: >=3.8
Requires-Dist: numpy
Requires-Dist: pyyaml
